README.rst
setup.py
tmdb/__init__.py
tmdb/route/__init__.py
tmdb/route/base.py
tmdb/route/collection.py
tmdb/route/company.py
tmdb/route/credit.py
tmdb/route/find.py
tmdb/route/keyword.py
tmdb/route/movie.py
tmdb/route/network.py
tmdb/route/person.py
tmdb/route/tv_episode.py
tmdb/route/tv_season.py
tmdb/route/tv_show.py
tmdb/schema/__init__.py
tmdb/schema/alternative_name.py
tmdb/schema/collection.py
tmdb/schema/company.py
tmdb/schema/country.py
tmdb/schema/credit.py
tmdb/schema/external_id.py
tmdb/schema/find.py
tmdb/schema/genre.py
tmdb/schema/image.py
tmdb/schema/keyword.py
tmdb/schema/language.py
tmdb/schema/media.py
tmdb/schema/movie.py
tmdb/schema/person.py
tmdb/schema/provider.py
tmdb/schema/title.py
tmdb/schema/translaction.py
tmdb/schema/tv_episode.py
tmdb/schema/tv_season.py
tmdb/schema/tv_show.py
tmdb/schema/video.py
tmdb_python.egg-info/PKG-INFO
tmdb_python.egg-info/SOURCES.txt
tmdb_python.egg-info/dependency_links.txt
tmdb_python.egg-info/not-zip-safe
tmdb_python.egg-info/requires.txt
tmdb_python.egg-info/top_level.txt